llm_fingerprint/__init__.py
llm_fingerprint/cli.py
llm_fingerprint/commands.py
llm_fingerprint/io.py
llm_fingerprint/mixin.py
llm_fingerprint/models.py
llm_fingerprint/services.py
llm_fingerprint/storage/__init__.py
llm_fingerprint/storage/base.py
llm_fingerprint/storage/implementation/__init__.py
llm_fingerprint/storage/implementation/chroma.py
llm_fingerprint/storage/implementation/qdrant.py
llm_fingerprint-0.6.0.dist-info/METADATA
llm_fingerprint-0.6.0.dist-info/WHEEL
llm_fingerprint-0.6.0.dist-info/entry_points.txt
llm_fingerprint-0.6.0.dist-info/licenses/LICENSE
llm_fingerprint-0.6.0.dist-info/RECORD
