Metadata-Version: 2.4
Name: llm_fingerprint
Version: 0.6.0
Summary: Identify LLMs by their response fingerprints
Project-URL: Repository, https://github.com/S1M0N38/llm-fingerprint.git
Project-URL: Issues, https://github.com/S1M0N38/llm-fingerprint/issues
Project-URL: Changelog, https://github.com/S1M0N38/llm-fingerprint/blob/main/CHANGELOG.md
Author-email: S1M0N38 <bertolottosimone@gmail.com>
License-Expression: MIT
License-File: LICENSE
Classifier: Development Status :: 1 - Planning
Classifier: License :: OSI Approved :: MIT License
Classifier: Programming Language :: Python :: 3
Requires-Python: >=3.11
Requires-Dist: aiofiles>=24.1.0
Requires-Dist: chromadb>=0.6.3
Requires-Dist: httpx>=0.28.1
Requires-Dist: openai>=1.66.3
Requires-Dist: pydantic>=2.10.6
Requires-Dist: qdrant-client>=1.13.3
Requires-Dist: tqdm>=4.67.1
